pyverified/__init__.py
pyverified/exc.py
pyverified/msg.py
pyverified/version.py
pyverified/frame/__init__.py
pyverified/frame/fastapi.py
pyverified/frame/flask.py
pyverified/verify/__init__.py
pyverified/verify/_unset.py
pyverified/verify/base.py
pyverified/verify/type_.py
pyverified/verify/verify.py
pyverified-2024.10.11.dist-info/LICENSE
pyverified-2024.10.11.dist-info/METADATA
pyverified-2024.10.11.dist-info/WHEEL
pyverified-2024.10.11.dist-info/top_level.txt
pyverified-2024.10.11.dist-info/RECORD
