Metadata-Version: 2.1
Name: pyverified
Version: 2024.10.11
Summary: Parameter verification framework based on Python.
Home-page: https://github.com/xccx0823/pyverified
Author: Ethan
Author-email: cheerxiong0823@163.com
License: UNKNOWN
Platform: UNKNOWN
Classifier: Programming Language :: Python :: 3
Classifier: License :: OSI Approved :: MIT License
Classifier: Operating System :: OS Independent
License-File: LICENSE
